redes_bayesianas_20074/__init__.py
redes_bayesianas_20074/bayesian_library.py
redes_bayesianasv2_rey20074-0.0.2.dist-info/LICENSE
redes_bayesianasv2_rey20074-0.0.2.dist-info/METADATA
redes_bayesianasv2_rey20074-0.0.2.dist-info/WHEEL
redes_bayesianasv2_rey20074-0.0.2.dist-info/top_level.txt
redes_bayesianasv2_rey20074-0.0.2.dist-info/RECORD
