Metadata-Version: 2.1
Name: redes-bayesianasv2-rey20074
Version: 0.0.2
Summary: Una libreria para construir redes bayesianas y realizar inferencia probabilística
Home-page: https://github.com/MarianoReyes/redes_bayesianas_package
Author: Jose Reyes
Author-email: josemarianoreyesh02@gmail.com
Project-URL: Bug Tracker, https://github.com/pypa/sampleproject/issues
Classifier: Programming Language :: Python :: 3
Classifier: License :: OSI Approved :: MIT License
Classifier: Operating System :: OS Independent
Requires-Python: >=3.6
License-File: LICENSE
